Web_Scraping_Utility-1.0.0.dist-info/DESCRIPTION.rst
Web_Scraping_Utility-1.0.0.dist-info/METADATA
Web_Scraping_Utility-1.0.0.dist-info/RECORD
Web_Scraping_Utility-1.0.0.dist-info/WHEEL
Web_Scraping_Utility-1.0.0.dist-info/metadata.json
Web_Scraping_Utility-1.0.0.dist-info/top_level.txt
web_scraping/__init__.py
web_scraping/web_scraping.py
